pytest_qaseio/__init__.py
pytest_qaseio/api_client.py
pytest_qaseio/constants.py
pytest_qaseio/converter.py
pytest_qaseio/debug_info.py
pytest_qaseio/hooks.py
pytest_qaseio/plugin.py
pytest_qaseio/plugin_exceptions.py
pytest_qaseio/py.typed
pytest_qaseio/storage.py
pytest_qaseio-2.7.1.dist-info/METADATA
pytest_qaseio-2.7.1.dist-info/WHEEL
pytest_qaseio-2.7.1.dist-info/entry_points.txt
pytest_qaseio-2.7.1.dist-info/licenses/LICENSE
pytest_qaseio-2.7.1.dist-info/RECORD
