Metadata-Version: 2.4
Name: pytest-qaseio
Version: 2.7.1
Summary: Pytest plugin for Qase.io integration
License-Expression: MIT
License-File: LICENSE
Keywords: pytest,qase,qaseio,selenium,autotests
Author: Saritasa
Author-email: pypi@saritasa.com
Requires-Python: >=3.11
Classifier: Development Status :: 5 - Production/Stable
Classifier: License :: OSI Approved :: MIT License
Classifier: Intended Audience :: Developers
Classifier: Operating System :: OS Independent
Classifier: Framework :: Pytest
Classifier: Topic :: Software Development :: Libraries :: Python Modules
Classifier: Topic :: Software Development :: Bug Tracking
Classifier: Topic :: Software Development :: Testing
Provides-Extra: selenium
Requires-Dist: arrow (>=1.2.3,<2.0.0)
Requires-Dist: filelock (>=3.14.0,<4.0.0)
Requires-Dist: pytest (>=7.2.2)
Requires-Dist: qase-api-client (>=1.1.1,<2.0.0)
Requires-Dist: requests (>=2.23.0,<3.0.0)
Requires-Dist: selenium (>=4.21.0,<4.32.0) ; extra == "selenium"
Requires-Dist: tenacity (>=9.1.2,<10.0.0)
Project-URL: Homepage, https://pypi.org/project/pytest-qaseio/
Project-URL: Repository, https://github.com/saritasa-nest/pytest-qaseio
Project-URL: changelog, https://github.com/saritasa-nest/pytest-qaseio/blob/main/CHANGELOG.md
Project-URL: releasenotes, https://github.com/saritasa-nest/pytest-qaseio/releases
